AUTHORS.rst
CONTRIBUTING.rst
HISTORY.rst
LICENSE
MANIFEST.in
README.rst
setup.py
mysql_statsd/__init__.py
mysql_statsd/mysql_statsd.py
mysql_statsd/thread_base.py
mysql_statsd/thread_manager.py
mysql_statsd/thread_mysql.py
mysql_statsd/thread_statsd.py
mysql_statsd.egg-info/PKG-INFO
mysql_statsd.egg-info/SOURCES.txt
mysql_statsd.egg-info/dependency_links.txt
mysql_statsd.egg-info/entry_points.txt
mysql_statsd.egg-info/not-zip-safe
mysql_statsd.egg-info/requires.txt
mysql_statsd.egg-info/top_level.txt
mysql_statsd/preprocessors/.innodb_preprocessor.py.swp
mysql_statsd/preprocessors/__init__.py
mysql_statsd/preprocessors/__init__.pyc
mysql_statsd/preprocessors/columns_preprocessor.py
mysql_statsd/preprocessors/columns_preprocessor.pyc
mysql_statsd/preprocessors/innodb_preprocessor.py
mysql_statsd/preprocessors/innodb_preprocessor.pyc
mysql_statsd/preprocessors/interface.py
mysql_statsd/preprocessors/interface.pyc
mysql_statsd/preprocessors/mysql_preprocessor.py
mysql_statsd/preprocessors/mysql_preprocessor.pyc