Metadata-Version: 1.1
Name: mysql-statsd
Version: 0.1.5
Summary: Daemon that gathers statistics from MySQL and sends them to statsd.
Home-page: https://github.com/spilgames/mysql-statsd
Author: Jasper Capel, Thijs de Zoete
Author-email: jasper.capel@spilgames.com
License: BSD
Keywords: mysql_statsd
Platform: UNKNOWN
Classifier: Development Status :: 2 - Pre-Alpha
Classifier: Intended Audience :: Developers
Classifier: License :: OSI Approved :: BSD License
Classifier: Natural Language :: English
Classifier: Programming Language :: Python :: 2
Classifier: Programming Language :: Python :: 2.6
Classifier: Programming Language :: Python :: 2.7
Classifier: Programming Language :: Python :: 3
Classifier: Programming Language :: Python :: 3.3
